py_iec61850_cdc/__init__.py
py_iec61850_cdc/abstracts.py
py_iec61850_cdc/basetypes.py
py_iec61850_cdc/controls.py
py_iec61850_cdc/description.py
py_iec61850_cdc/enums.py
py_iec61850_cdc/factory.py
py_iec61850_cdc/listobjects.py
py_iec61850_cdc/logical_nodes.py
py_iec61850_cdc/measurand.py
py_iec61850_cdc/measurand_harmonics.py
py_iec61850_cdc/prescond.py
py_iec61850_cdc/service.py
py_iec61850_cdc/settings.py
py_iec61850_cdc/status.py
py_iec61850_cdc/attributes/__init__.py
py_iec61850_cdc/attributes/analoguevalues.py
py_iec61850_cdc/attributes/calendartime.py
py_iec61850_cdc/attributes/cell.py
py_iec61850_cdc/attributes/checkconditions.py
py_iec61850_cdc/attributes/detailqual.py
py_iec61850_cdc/attributes/entrytime.py
py_iec61850_cdc/attributes/lcblogentryoptions.py
py_iec61850_cdc/attributes/originator.py
py_iec61850_cdc/attributes/point.py
py_iec61850_cdc/attributes/pulseconfig.py
py_iec61850_cdc/attributes/quality.py
py_iec61850_cdc/attributes/rangeconfig.py
py_iec61850_cdc/attributes/rcbreportoptions.py
py_iec61850_cdc/attributes/reasonforinclusioninlog.py
py_iec61850_cdc/attributes/reasonforinclusioninreport.py
py_iec61850_cdc/attributes/scaledvalueconfig.py
py_iec61850_cdc/attributes/svmessageoptions.py
py_iec61850_cdc/attributes/timequality.py
py_iec61850_cdc/attributes/timestamp.py
py_iec61850_cdc/attributes/triggerconditions.py
py_iec61850_cdc/attributes/unit.py
py_iec61850_cdc/attributes/utils.py
py_iec61850_cdc/attributes/valwithtrans.py
py_iec61850_cdc/attributes/vector.py
py_iec61850_cdc-0.1.3.dist-info/METADATA
py_iec61850_cdc-0.1.3.dist-info/WHEEL
py_iec61850_cdc-0.1.3.dist-info/licenses/LICENSE
py_iec61850_cdc-0.1.3.dist-info/RECORD
