Metadata-Version: 2.3
Name: py_iec61850_cdc
Version: 0.1.3
Summary: A package for Pythonic IEC 61850-7-3 common data classes.
Project-URL: Homepage, https://codeberg.org/khawkings/py_iec61850_cdc
Project-URL: Issues, https://codeberg.org/khawkings/py_iec61850_cdc/issues
Author-email: Kyle Hawkings <kyle.hawkings@gmail.com>
Classifier: Framework :: Pydantic :: 2
Classifier: License :: OSI Approved :: Apache Software License
Classifier: Programming Language :: Python :: 3 :: Only
Classifier: Topic :: Scientific/Engineering
Classifier: Topic :: Software Development :: Libraries :: Python Modules
Requires-Python: >=3.9
Requires-Dist: pydantic>=2.0
